LICENSE
README.md
setup.py
lemondb/__init__.py
lemondb/constants.py
lemondb/database.py
lemondb/errors.py
lemondb/globals.py
lemondb/logger.py
lemondb/query.py
lemondb/server.py
lemondb/storage.py
lemondb/utils.py
lemondb.egg-info/PKG-INFO
lemondb.egg-info/SOURCES.txt
lemondb.egg-info/dependency_links.txt
lemondb.egg-info/requires.txt
lemondb.egg-info/top_level.txt
lemondb/middleware/__init__.py
lemondb/middleware/base.py
lemondb/middleware/json.py
lemondb/middleware/sidle.py
lemondb/plugin/__init__.py
lemondb/plugin/base.py
lemondb/plugin/lemon.py
lemondb/plugin/sidle.py
lemondb/serializer/__init__.py
lemondb/serializer/base.py
lemondb/serializer/json.py
lemondb/types/__init__.py