Metadata-Version: 2.1
Name: lemondb
Version: 1.0.3
Summary: Simple and lightweight document oriented database
Home-page: UNKNOWN
Author: Zenqi
License: MIT
Platform: UNKNOWN
Provides-Extra: logger
Provides-Extra: crypto
Provides-Extra: cli
License-File: LICENSE
